toolforge_weld/__init__.py
toolforge_weld/api_client.py
toolforge_weld/config.py
toolforge_weld/errors.py
toolforge_weld/kubernetes.py
toolforge_weld/kubernetes_config.py
toolforge_weld/py.typed
toolforge_weld/utils.py
toolforge_weld/logs/__init__.py
toolforge_weld/logs/kubernetes.py
toolforge_weld/logs/source.py
toolforge_weld-1.6.12.dist-info/licenses/LICENSE
toolforge_weld-1.6.12.dist-info/METADATA
toolforge_weld-1.6.12.dist-info/WHEEL
toolforge_weld-1.6.12.dist-info/top_level.txt
toolforge_weld-1.6.12.dist-info/RECORD
