Metadata-Version: 2.4
Name: toolforge-weld
Version: 1.6.12
Summary: Shared Python code for Toolforge infrastructure components
Author: Taavi Väänänen
Author-email: hi@taavi.wtf
License: AGPL-3.0-or-later
Classifier: Development Status :: 4 - Beta
Classifier: Intended Audience :: System Administrators
Classifier: License :: OSI Approved :: GNU Affero General Public License v3 or later (AGPLv3+)
Classifier: Operating System :: POSIX :: Linux
Classifier: Programming Language :: Python :: 3
Classifier: Typing :: Typed
Requires-Python: >=3.9
License-File: LICENSE
Requires-Dist: python-dateutil
Requires-Dist: PyYAML
Requires-Dist: requests
Requires-Dist: pyOpenSSL
Requires-Dist: click<9.0.0,>=8.0.3
Dynamic: author
Dynamic: author-email
Dynamic: classifier
Dynamic: description
Dynamic: description-content-type
Dynamic: license
Dynamic: license-file
Dynamic: requires-dist
Dynamic: requires-python
Dynamic: summary
